Workbook

Sheet Requisitos
A1: Matriz de requisitos · Clancy's Rewards
A2: Capstone 001V · Andy Aravena Auquilen · Estado al 29 de octubre de 2026
A4: ID | B4: Tipo | C4: Categoría | D4: Requisito | E4: Descripción | F4: Actor | G4: Prioridad | H4: Criterio de aceptación | I4: Origen | J4: Estado | K4: Sprint | L4: Issue | M4: Evidencia en el sistema
A5: RF-01 | B5: Funcional | C5: Cuentas | D5: Registro con correo y contraseña | E5: El cliente crea su cuenta con nombre, correo y contraseña, y queda inscrito en el programa con 0 visitas. | F5: Cliente | G5: Alta | H5: Con un correo no registrado y una contraseña de al menos 6 caracteres, se crea la cuenta y su membresía. Con un correo ya registrado, se muestra un error. | I5: Análisis del proceso del local | J5: Implementado | K5: Prototipo | M5: POST /api/auth/register · pantalla Registro
A6: RF-02 | B6: Funcional | C6: Cuentas | D6: Inicio de sesión con correo o con Google | E6: El usuario entra con su correo y contraseña o con su cuenta de Google, y la app lo lleva a las pantallas de su rol. | F6: Todos | G6: Alta | H6: Con credenciales válidas se entrega un token de sesión; con credenciales inválidas se responde error 401; una cuenta desactivada no puede entrar. | I6: Análisis del proceso del local | J6: Parcial | K6: Sprint 2 | L6: #50 | M6: POST /api/auth/login · POST /api/auth/google
A7: RF-03 | B7: Funcional | C7: Fidelización | D7: Tarjeta de socio | E7: El cliente ve sus visitas acumuladas y cuánto le falta para el próximo premio. | F7: Cliente | G7: Alta | H7: La tarjeta muestra el número de visitas y el próximo premio según las visitas requeridas. | I7: Análisis del proceso del local | J7: Implementado | K7: Prototipo | M7: GET /api/loyalty · pantalla Tarjeta de socio
A8: RF-04 | B8: Funcional | C8: Fidelización | D8: QR personal de un solo uso | E8: El cliente genera un código QR para registrar su visita o canjear un premio. | F8: Cliente | G8: Alta | H8: El QR vence a los 3 minutos (180 s) y deja de servir después de escanearse una vez. | I8: Problema de la tarjeta de papel (sellos copiables) | J8: Implementado | K8: Prototipo | M8: POST /api/qr/generate · colección qr_tokens
A9: RF-05 | B9: Funcional | C9: Fidelización | D9: Escaneo del QR y suma de visita | E9: El personal escanea el QR con la cámara del teléfono y la visita se suma al cliente. | F9: Personal | G9: Alta | H9: Solo un rol de personal puede escanear. Un QR vencido o ya usado se rechaza. La visita queda registrada con el empleado que la validó. | I9: Análisis del proceso del local | J9: Implementado | K9: Prototipo | M9: POST /api/qr/scan · colección visit_log
A10: RF-06 | B10: Funcional | C10: Fidelización | D10: Canje de premios en dos pasos | E10: El escaneo reserva el premio y descuenta las visitas; quien lo lleva a la mesa confirma la entrega. | F10: Cliente / Personal | G10: Alta | H10: Sin visitas suficientes el canje se rechaza. El canje queda "pendiente" hasta confirmar la entrega, y confirmar dos veces no lo duplica. | I10: Análisis del proceso de atención | J10: Implementado | K10: Prototipo | M10: POST /api/redemptions/{id}/deliver
A11: RF-07 | B11: Funcional | C11: Contenido | D11: Menú del local | E11: El cliente consulta el menú por servicio y sección, con precios y disponibilidad. | F11: Cliente | G11: Media | H11: Se muestran los platos disponibles ordenados por servicio y sección. | I11: Análisis del proceso del local | J11: Implementado | K11: Prototipo | M11: GET /api/menu · 43 platos reales
A12: RF-08 | B12: Funcional | C12: Administración | D12: Gestión de menú, premios y promociones | E12: La administración crea, edita y desactiva platos, premios y promociones desde la app. | F12: Administrador | G12: Alta | H12: Solo los roles de administración pueden editar. Los cambios se ven en la app del cliente sin publicar una nueva versión. | I12: Análisis del proceso del local | J12: Implementado | K12: Prototipo | M12: /api/admin/menu · /rewards · /promotions
A13: RF-09 | B13: Funcional | C13: Administración | D13: Panel de indicadores | E13: La administración ve clientes, socios activos, visitas del día y de la semana, y premios más canjeados. | F13: Administrador | G13: Media | H13: El panel muestra los indicadores calculados desde los registros reales de visitas y canjes. | I13: Problema: el local no tiene datos de sus clientes | J13: Implementado | K13: Prototipo | M13: GET /api/admin/dashboard
A14: RF-10 | B14: Funcional | C14: Administración | D14: Gestión del personal | E14: El dueño crea, edita y desactiva cuentas del personal con su rol. | F14: Dueño | G14: Media | H14: Solo el dueño accede a esta función; un empleado desactivado no puede iniciar sesión. | I14: Análisis del proceso del local | J14: Implementado | K14: Prototipo | M14: /api/admin/staff
A15: RF-11 | B15: Funcional | C15: Usabilidad | D15: Confirmar antes de borrar y deshacer | E15: Antes de eliminar un plato, premio o promoción, la app pide confirmación y permite deshacer. | F15: Administrador | G15: Media | H15: Ninguna eliminación ocurre sin confirmar; durante unos segundos se puede deshacer. | I15: Auditoría de usabilidad del prototipo | J15: Pendiente | K15: Sprint 1 | L15: #43 | M15: HU-14
A16: RF-12 | B16: Funcional | C16: Usabilidad | D16: Mensajes de error y reintentar | E16: Si falla la conexión o una operación, la app muestra un mensaje claro y permite reintentar. | F16: Todos | G16: Media | H16: Cada error de red muestra un mensaje en pantalla con un botón para reintentar. | I16: Auditoría de usabilidad del prototipo | J16: Pendiente | K16: Sprint 1 | L16: #44 | M16: HU-15
A17: RF-13 | B17: Funcional | C17: Cuentas | D17: Recuperación de contraseña | E17: El cliente recupera el acceso a su cuenta mediante un correo. | F17: Cliente | G17: Media | H17: Al solicitarlo, llega un enlace al correo que permite definir una nueva contraseña. | I17: Análisis del proceso del local | J17: Pendiente | K17: Sprint 3 | L17: #57 | M17: HU-04
A18: RF-14 | B18: Funcional | C18: Fidelización | D18: Tiempo mínimo entre visitas | E18: El sistema evita sumar dos visitas al mismo cliente en un intervalo corto. | F18: Personal | G18: Media | H18: Un segundo escaneo del mismo cliente dentro del intervalo configurado se rechaza. | I18: Prevención de abuso del programa | J18: Pendiente | K18: Sprint 3 | L18: #56 | M18: HU-08
A19: RF-15 | B19: Funcional | C19: Privacidad | D19: Exportar y borrar la cuenta | E19: El cliente descarga sus datos y puede eliminar su cuenta desde la app. | F19: Cliente | G19: Alta | H19: El cliente obtiene un archivo con sus datos y, al borrar la cuenta, sus datos personales se eliminan. | I19: RGPD (UE) 2016/679 | J19: Pendiente | K19: Sprint 3 | L19: #54 | M19: HU-19
A20: RF-16 | B20: Funcional | C20: Cuentas | D20: Inicio de sesión con Apple | E20: En iPhone, el cliente puede entrar con su cuenta de Apple, como alternativa al inicio de sesión con Google. | F20: Cliente | G20: Alta | H20: En la app de iOS aparece el botón "Iniciar sesión con Apple"; el servidor valida el token de Apple y crea o recupera la cuenta. | I20: Guía de revisión de App Store 4.8 (por usar login con Google) | J20: Pendiente | K20: Sprint 2 | L20: #66 | M20: HU-20
A21: RNF-01 | B21: No funcional | C21: Seguridad | D21: Contraseñas cifradas | E21: Las contraseñas se guardan con un hash bcrypt, nunca en texto plano. | F21: Sistema | G21: Alta | H21: En la base de datos solo existe el campo password_hash. | I21: OWASP Mobile Top 10 | J21: Implementado | K21: Prototipo | M21: Función hash_password
A22: RNF-02 | B22: No funcional | C22: Seguridad | D22: Sesiones con token JWT | E22: Cada petición se autentica con un token firmado que vence. | F22: Sistema | G22: Alta | H22: Una petición sin token o con un token vencido se responde con error 401. | I22: OWASP Mobile Top 10 | J22: Implementado | K22: Prototipo | M22: Funciones create_jwt y get_current_user
A23: RNF-03 | B23: No funcional | C23: Seguridad | D23: Permisos por rol en el servidor | E23: El servidor valida el rol en cada operación sensible, no solo la app. | F23: Sistema | G23: Alta | H23: Un cliente que llama a una ruta de administración recibe error 403. | I23: OWASP Mobile Top 10 | J23: Implementado | K23: Prototipo | M23: require_admin · require_owner
A24: RNF-04 | B24: No funcional | C24: Seguridad | D24: Credenciales fuera del código | E24: Claves, cadenas de conexión y contraseñas iniciales se leen desde variables de entorno. | F24: Sistema | G24: Alta | H24: El repositorio no contiene ninguna credencial; existe un .env.example sin valores. | I24: Buenas prácticas (Twelve-Factor App) | J24: Implementado | K24: Sprint 0 | L24: #36 | M24: backend/.env.example
A25: RNF-05 | B25: No funcional | C25: Seguridad | D25: Límite de intentos y CORS restringido | E25: Se limitan los intentos de login y de escaneo, y la API solo acepta orígenes conocidos. | F25: Sistema | G25: Alta | H25: Tras 5 intentos fallidos de login en 15 minutos, o más de 20 escaneos por minuto, la API responde error 429; un origen que no está en CORS_ORIGINS es rechazado. | I25: OWASP Mobile Top 10 | J25: Implementado | K25: Sprint 1 | L25: #42 | M25: backend/server.py · backend/tests/test_limite_intentos.py · Issues #41 y #42
A26: RNF-06 | B26: No funcional | C26: Usabilidad | D26: Botones táctiles accesibles | E26: Los botones del panel de administración miden al menos 44 px. | F26: Administrador | G26: Media | H26: Todos los botones del panel cumplen el tamaño mínimo. | I26: Auditoría de usabilidad del prototipo | J26: Pendiente | K26: Sprint 1 | L26: #45 | M26: Panel de administración
A27: RNF-07 | B27: No funcional | C27: Disponibilidad | D27: Servidor en la nube con HTTPS | E27: La API y la base de datos funcionan en la nube, en la Unión Europea, con respaldo diario. | F27: Sistema | G27: Alta | H27: La app de producción se conecta por HTTPS y la base tiene respaldo automático. | I27: RGPD y publicación en Google Play | J27: Pendiente | K27: Sprint 2 | L27: #47 | M27: Issues #47 y #48
A28: RNF-08 | B28: No funcional | C28: Privacidad | D28: Cumplimiento del RGPD | E28: Consentimiento, política de privacidad y derechos de acceso y borrado. | F28: Cliente | G28: Alta | H28: El registro exige aceptar la política; el cliente puede exportar y borrar sus datos. | I28: RGPD (UE) 2016/679 | J28: Pendiente | K28: Sprint 3 | L28: #54 | M28: HU-19
A29: RNF-09 | B29: No funcional | C29: Compatibilidad | D29: App en Android e iOS | E29: La app se publica en Google Play y en App Store, con una sola base de código (Expo). | F29: Sistema | G29: Alta | H29: Android: pasa la prueba cerrada de 14 días con al menos 12 testers. iOS: el build de EAS pasa TestFlight y la revisión de Apple. Ambas quedan publicadas. | I29: Retroalimentación docente: el 47 % de los teléfonos en Irlanda usa iOS | J29: Pendiente | K29: Sprint 2 y cierre | L29: #51 | M29: Android: #51, #53 y #60 · iOS: #65, #67, #69 y #70
A30: RNF-10 | B30: No funcional | C30: Mantenibilidad | D30: Contenido como datos | E30: Menú, premios y promociones son datos editables, no código. | F30: Administrador | G30: Media | H30: Agregar un plato o un premio no requiere publicar una nueva versión de la app. | I30: Buenas prácticas de diseño | J30: Implementado | K30: Prototipo | M30: backend/data/menu.clancys-cork.json
A31: RNF-11 | B31: No funcional | C31: Calidad | D31: Pruebas automatizadas | E31: Pruebas del backend y de la app, y prueba de usuario con el personal. | F31: Sistema | G31: Alta | H31: La suite de pruebas corre sin errores antes de cada entrega. | I31: Competencia: pruebas de certificación | J31: Parcial | K31: Sprint 3 | L31: #58 | M31: backend/tests (10 pruebas del límite de intentos) · Issues #58 y #59
A32: RNF-12 | B32: No funcional | C32: Compatibilidad | D32: Requisitos de publicación en App Store | E32: La app cumple las reglas de Apple: texto de permiso de cámara, política de privacidad, etiqueta de privacidad y borrado de cuenta dentro de la app. | F32: Sistema | G32: Alta | H32: La ficha de App Store está completa y la app no es rechazada en la revisión por estos puntos. | I32: Guía de revisión de App Store | J32: Pendiente | K32: Sprint 3 | L32: #68 | M32: Issues #68 y #70
A34: Leyenda: Estado y Prioridad se eligen de una lista. El estado se actualiza al cerrar el issue de cada requisito; el resumen se recalcula solo.
A35: Fuentes: análisis del proceso de atención de Clancy's Cork, backlog del repositorio, RGPD (UE) 2016/679, OWASP Mobile Top 10 y requisitos de Google Play.

Sheet Resumen
A1: Resumen de requisitos
A2: Se calcula desde la hoja Requisitos
A4: Tipo | B4: Total | C4: Implementado | D4: Parcial | E4: Pendiente | F4: % implementado
A5: Funcional | B5: =COUNTIF(Requisitos!$B$5:$B$32,A5) -> 16 | C5: =COUNTIFS(Requisitos!$B$5:$B$32,A5,Requisitos!$J$5:$J$32,"Implementado") -> 9 | D5: =COUNTIFS(Requisitos!$B$5:$B$32,A5,Requisitos!$J$5:$J$32,"Parcial") -> 1 | E5: =COUNTIFS(Requisitos!$B$5:$B$32,A5,Requisitos!$J$5:$J$32,"Pendiente") -> 6 | F5: =IF(B5=0,0,C5/B5) -> 0.5625
A6: No funcional | B6: =COUNTIF(Requisitos!$B$5:$B$32,A6) -> 12 | C6: =COUNTIFS(Requisitos!$B$5:$B$32,A6,Requisitos!$J$5:$J$32,"Implementado") -> 6 | D6: =COUNTIFS(Requisitos!$B$5:$B$32,A6,Requisitos!$J$5:$J$32,"Parcial") -> 1 | E6: =COUNTIFS(Requisitos!$B$5:$B$32,A6,Requisitos!$J$5:$J$32,"Pendiente") -> 5 | F6: =IF(B6=0,0,C6/B6) -> 0.5
A7: Total | B7: =SUM(B5:B6) -> 28 | C7: =SUM(C5:C6) -> 15 | D7: =SUM(D5:D6) -> 2 | E7: =SUM(E5:E6) -> 11 | F7: =IF(B7=0,0,C7/B7) -> 0.53571429
A9: Sprint | B9: Requisitos
A10: Prototipo | B10: =COUNTIF(Requisitos!$K$5:$K$32,"Prototipo*") -> 13
A11: Sprint 0 | B11: =COUNTIF(Requisitos!$K$5:$K$32,"Sprint 0*") -> 1
A12: Sprint 1 | B12: =COUNTIF(Requisitos!$K$5:$K$32,"Sprint 1*") -> 4
A13: Sprint 2 | B13: =COUNTIF(Requisitos!$K$5:$K$32,"Sprint 2*") -> 4
A14: Sprint 3 | B14: =COUNTIF(Requisitos!$K$5:$K$32,"Sprint 3*") -> 6
A16: El conteo por sprint incluye "Sprint 2 y cierre" dentro de Sprint 2.

Sheet Requisitos técnicos
A1: Requisitos técnicos: con qué se construye y se ejecuta la app
A2: Herramientas, tecnologías, servicios y hardware usados en el proyecto
A4: Ámbito | B4: Elemento | C4: Versión o plan | D4: Para qué se usa | E4: Costo mín. (USD) | F4: Costo máx. (USD)
A5: Hardware | B5: Computador con Windows 11 | C5: — | D5: Desarrollo del frontend y del backend | E5: 0 | F5: 0
A6: Hardware | B6: Teléfono Android | C6: — | D6: Pruebas de la app y del escaneo QR con cámara | E6: 0 | F6: 0
A7: Herramientas | B7: Visual Studio Code | C7: Actual | D7: Editor de código | E7: 0 | F7: 0
A8: Herramientas | B8: Git y GitHub | C8: Repositorio público | D8: Control de versiones, backlog (issues y milestones) y evidencias | E8: 0 | F8: 0
A9: Herramientas | B9: Expo Go | C9: SDK 54 | D9: Ejecutar la app en el teléfono durante el desarrollo | E9: 0 | F9: 0
A10: App móvil | B10: React Native | C10: 0.81.5 | D10: Interfaz de la app para Android | E10: 0 | F10: 0
A11: App móvil | B11: Expo | C11: ~54.0 | D11: Framework y herramientas de compilación de la app | E11: 0 | F11: 0
A12: App móvil | B12: TypeScript | C12: ~5.9 | D12: Lenguaje de la app con tipos | E12: 0 | F12: 0
A13: App móvil | B13: expo-router | C13: ~6.0 | D13: Navegación por roles: cliente, personal y administrador | E13: 0 | F13: 0
A14: App móvil | B14: expo-camera | C14: ~17.0 | D14: Leer el código QR con la cámara | E14: 0 | F14: 0
A15: App móvil | B15: react-native-qrcode-svg | C15: ^6.3 | D15: Dibujar el QR del cliente | E15: 0 | F15: 0
A16: App móvil | B16: expo-secure-store | C16: ~15.0 | D16: Guardar la sesión de forma segura en el teléfono | E16: 0 | F16: 0
... A33: App móvil | B33: expo-apple-authentication | C33: SDK 54 | D33: Inicio de sesión con Apple en iOS | E33: 0 | F33: 0
D34: Costo total estimado del proyecto | E34: =SUM(E5:E33) -> 134 | F34: =SUM(F5:F33) -> 183
A36: Fuentes de los costos: documento de definición del proyecto (Fase 1); Apple Developer Program (developer.apple.com); planes de Expo (expo.dev/pricing); MacinCloud (macincloud.com). Las versiones salen de package.json y requirements.txt.
